openfisca_extension_template/__init__.py
openfisca_extension_template/parameters/local_town/child_allowance/amount.yaml
openfisca_extension_template/parameters/local_town/child_allowance/index.yaml
openfisca_extension_template/parameters/local_town/index.yaml
openfisca_extension_template/variables/__init__.py
openfisca_extension_template/variables/local_benefit.py
tests/openfisca_extension_template/local_benefit.yaml
tests/openfisca_extension_template/test_api.py
openfisca_extension_template-2.0.7.dist-info/LICENSE
openfisca_extension_template-2.0.7.dist-info/METADATA
openfisca_extension_template-2.0.7.dist-info/WHEEL
openfisca_extension_template-2.0.7.dist-info/RECORD
