Metadata-Version: 2.3
Name: openfisca-extension_template
Version: 2.0.7
Summary: An OpenFisca extension that adds some variables to an already-existing tax and benefit system.
License: AGPL-3.0-only
Keywords: microsimulation,tax,benefit,rac,rules-as-code
Author: OpenFisca Team
Author-email: contact@openfisca.org
Maintainer: OpenFisca Team
Maintainer-email: contact@openfisca.org
Requires-Python: >=3.9,<3.14
Classifier: Development Status :: 5 - Production/Stable
Classifier: License :: OSI Approved :: GNU Affero General Public License v3
Classifier: Operating System :: POSIX
Classifier: Programming Language :: Python
Classifier: Programming Language :: Python :: 3
Classifier: Programming Language :: Python :: 3.9
Classifier: Programming Language :: Python :: 3.10
Classifier: Programming Language :: Python :: 3.11
Classifier: Programming Language :: Python :: 3.12
Classifier: Programming Language :: Python :: 3.13
Classifier: Topic :: Scientific/Engineering :: Information Analysis
Provides-Extra: ci
Provides-Extra: dev
Requires-Dist: codespell (>=2.3.0,<3.0.0) ; extra == "dev"
Requires-Dist: isort (>=5.13.2,<6.0.0) ; extra == "dev"
Requires-Dist: mdformat-footnote (>=0.1.1,<0.2.0) ; extra == "dev"
Requires-Dist: mdformat-frontmatter (>=2.0.8,<3.0.0) ; extra == "dev"
Requires-Dist: mdformat-gfm (>=0.3.6,<0.4.0) ; extra == "dev"
Requires-Dist: mdformat-gfm-alerts (>=1.0.1,<2.0.0) ; extra == "dev"
Requires-Dist: openfisca-country_template (>=8)
Requires-Dist: pyproject-fmt (>=2.4.3,<3.0.0) ; extra == "dev"
Requires-Dist: ruff (>=0.6.9,<0.7.0) ; extra == "dev"
Requires-Dist: ruff-lsp (>=0.0.57,<0.0.58) ; extra == "dev"
Requires-Dist: shellcheck-py (>=0.10.0.1,<0.11.0.0) ; extra == "dev"
Requires-Dist: shfmt-py (>=3.7.0.1,<4.0.0.0) ; extra == "dev"
Requires-Dist: twine (>=5.1.1,<6.0.0) ; extra == "ci"
Requires-Dist: yamllint (>=1.35.1,<2.0.0) ; extra == "dev"
Project-URL: Documentation, https://openfisca.org/doc
Project-URL: Homepage, https://openfisca.org
Project-URL: Repository, https://github.com/openfisca/extension-template
